README.md
setup.cfg
setup.py
cjwparquet/__init__.py
cjwparquet.egg-info/PKG-INFO
cjwparquet.egg-info/SOURCES.txt
cjwparquet.egg-info/dependency_links.txt
cjwparquet.egg-info/requires.txt
cjwparquet.egg-info/top_level.txt
cjwparquet.egg-info/zip-safe