Metadata-Version: 2.1
Name: cjwparquet
Version: 2.1.0
Summary: Utilities to help build Workbench modules
Home-page: http://github.com/CJWorkbench/cjwparquet/
Author: Adam Hooper
Author-email: adam@adamhooper.com
License: MIT
Platform: UNKNOWN
Provides-Extra: tests
